{"cells":[{"x":2,"y":-6,"z":-2,"value":0.041746963},{"x":2,"y":-6,"z":-1,"value":0.061017144},{"x":2,"y":-6,"z":0,"value":0.055390608},{"x":2,"y":-6,"z":1,"value":0.018299937},{"x":0,"y":-6,"z":-3,"value":0.1119362},{"x":0,"y":-6,"z":-2,"value":0.20107049},{"x":0,"y":-6,"z":-1,"value":0.24119036},{"x":0,"y":-6,"z":0,"value":0.23119298},{"x":0,"y":-6,"z":1,"value":0.16159153},{"x":0,"y":-6,"z":2,"value":0.031131888},{"x":-2,"y":-6,"z":-3,"value":0.074114814},{"x":-2,"y":-6,"z":-2,"value":0.23231462},{"x":-2,"y":-6,"z":-1,"value":0.27508283},{"x":-2,"y":-6,"z":0,"value":0.23857662},{"x":-2,"y":-6,"z":1,"value":0.13494496},{"x":4,"y":-5,"z":-2,"value":0.046191502},{"x":4,"y":-5,"z":-1,"value":0.07435762},{"x":4,"y":-5,"z":0,"value":0.06526393},{"x":4,"y":-5,"z":1,"value":0.011196149},{"x":2,"y":-5,"z":-4,"value":0.23993504},{"x":2,"y":-5,"z":-3,"value":0.3583769},{"x":2,"y":-5,"z":-2,"value":0.31346735},{"x":2,"y":-5,"z":-1,"value":0.30402285},{"x":2,"y":-5,"z":0,"value":0.31012458},{"x":2,"y":-5,"z":1,"value":0.34877786},{"x":2,"y":-5,"z":2,"value":0.34745556},{"x":2,"y":-5,"z":3,"value":0.06712989},{"x":0,"y":-5,"z":-5,"value":0.132359},{"x":0,"y":-5,"z":-4,"value":0.34408543},{"x":0,"y":-5,"z":-3,"value":0.29208753},{"x":0,"y":-5,"z":-2,"value":0.24971452},{"x":0,"y":-5,"z":-1,"value":0.19272329},{"x":0,"y":-5,"z":0,"value":0.2236962},{"x":0,"y":-5,"z":1,"value":0.27919483},{"x":0,"y":-5,"z":2,"value":0.30512032},{"x":0,"y":-5,"z":3,"value":0.30143812},{"x":-2,"y":-5,"z":-5,"value":0.055759586},{"x":-2,"y":-5,"z":-4,"value":0.3705749},{"x":-2,"y":-5,"z":-3,"value":0.30379754},{"x":-2,"y":-5,"z":-2,"value":0.2293951},{"x":-2,"y":-5,"z":-1,"value":0.24044158},{"x":-2,"y":-5,"z":0,"value":0.21994714},{"x":4,"y":-4,"z":-4,"value":0.044638347},{"x":-2,"y":-5,"z":1,"value":0.27913263},{"x":4,"y":-4,"z":-3,"value":0.26267523},{"x":-2,"y":-5,"z":2,"value":0.3451356},{"x":4,"y":-4,"z":-2,"value":0.35094008},{"x":-2,"y":-5,"z":3,"value":0.22558999},{"x":4,"y":-4,"z":-1,"value":0.3531103},{"x":4,"y":-4,"z":0,"value":0.3405155},{"x":-4,"y":-5,"z":-4,"value":0.028998435},{"x":4,"y":-4,"z":1,"value":0.32236502},{"x":-4,"y":-5,"z":-3,"value":0.28024656},{"x":4,"y":-4,"z":2,"value":0.16778535},{"x":-4,"y":-5,"z":-2,"value":0.37300977},{"x":-4,"y":-5,"z":-1,"value":0.37423888},{"x":2,"y":-4,"z":-5,"value":0.28157938},{"x":-4,"y":-5,"z":0,"value":0.3710625},{"x":2,"y":-4,"z":-4,"value":0.31730753},{"x":-4,"y":-5,"z":1,"value":0.3369924},{"x":2,"y":-4,"z":-3,"value":0.08171567},{"x":-4,"y":-5,"z":2,"value":0.13228485},{"x":2,"y":-4,"z":-2,"value":0.015159607},{"x":2,"y":-4,"z":2,"value":0.15958008},{"x":2,"y":-4,"z":3,"value":0.43226156},{"x":0,"y":-4,"z":-5,"value":0.3485597},{"x":0,"y":-4,"z":-4,"value":0.16923389},{"x":0,"y":-4,"z":-2,"value":0.011619486},{"x":0,"y":-4,"z":-1,"value":0.0802565},{"x":0,"y":-4,"z":0,"value":0.046347603},{"x":0,"y":-4,"z":2,"value":0.07039594},{"x":0,"y":-4,"z":3,"value":0.35957697},{"x":0,"y":-4,"z":4,"value":0.040691305},{"x":-2,"y":-4,"z":-5,"value":0.3504211},{"x":-2,"y":-4,"z":-4,"value":0.18138954},{"x":-2,"y":-4,"z":-1,"value":0.01369302},{"x":-2,"y":-4,"z":0,"value":0.011804},{"x":4,"y":-3,"z":-4,"value":0.28113192},{"x":4,"y":-3,"z":-3,"value":0.36815813},{"x":-2,"y":-4,"z":2,"value":0.097372346},{"x":4,"y":-3,"z":-2,"value":0.31170303},{"x":-2,"y":-4,"z":3,"value":0.3822262},{"x":4,"y":-3,"z":-1,"value":0.29674914},{"x":-2,"y":-4,"z":4,"value":0.028395165},{"x":4,"y":-3,"z":0,"value":0.30042964},{"x":-4,"y":-4,"z":-4,"value":0.35102245},{"x":4,"y":-3,"z":1,"value":0.3353704},{"x":-4,"y":-4,"z":-3,"value":0.3260745},{"x":4,"y":-3,"z":2,"value":0.35904616},{"x":-4,"y":-4,"z":-2,"value":0.24169794},{"x":4,"y":-3,"z":3,"value":0.09445328},{"x":2,"y":-3,"z":-6,"value":0.03019395},{"x":-4,"y":-4,"z":-1,"value":0.19762126},{"x":2,"y":-3,"z":-5,"value":0.3677999},{"x":-4,"y":-4,"z":0,"value":0.19794595},{"x":2,"y":-3,"z":-4,"value":0.036171824},{"x":-4,"y":-4,"z":1,"value":0.24606764},{"x":-4,"y":-4,"z":2,"value":0.36682868},{"x":2,"y":-3,"z":-2,"value":0.029269062},{"x":-4,"y":-4,"z":3,"value":0.2279897},{"x":2,"y":-3,"z":-1,"value":0.03776194},{"x":2,"y":-3,"z":0,"value":0.03755427},{"x":2,"y":-3,"z":1,"value":0.027867712},{"x":0,"y":-3,"z":-6,"value":0.16781089},{"x":2,"y":-3,"z":3,"value":0.28353837},{"x":0,"y":-3,"z":-5,"value":0.2626382},{"x":2,"y":-3,"z":4,"value":0.049437977},{"x":0,"y":-3,"z":-3,"value":0.14940488},{"x":0,"y":-3,"z":-2,"value":0.045069225},{"x":0,"y":-3,"z":-1,"value":0.06176251},{"x":0,"y":-3,"z":0,"value":0.062384106},{"x":0,"y":-3,"z":1,"value":0.104876846},{"x":0,"y":-3,"z":3,"value":0.23603687},{"x":-2,"y":-3,"z":-6,"value":0.06421395},{"x":0,"y":-3,"z":4,"value":0.1536921},{"x":-2,"y":-3,"z":-5,"value":0.31885117},{"x":-2,"y":-3,"z":-3,"value":0.029813267},{"x":-2,"y":-3,"z":-2,"value":0.0937994},{"x":-2,"y":-3,"z":-1,"value":0.11024325},{"x":4,"y":-2,"z":-5,"value":0.079407156},{"x":-2,"y":-3,"z":0,"value":0.0902883},{"x":4,"y":-2,"z":-4,"value":0.35630307},{"x":-2,"y":-3,"z":1,"value":0.048469625},{"x":4,"y":-2,"z":-3,"value":0.31910774},{"x":4,"y":-2,"z":-2,"value":0.29745376},{"x":-2,"y":-3,"z":3,"value":0.24962324},{"x":4,"y":-2,"z":-1,"value":0.31352493},{"x":-2,"y":-3,"z":4,"value":0.17294988},{"x":-4,"y":-3,"z":-5,"value":0.19437899},{"x":4,"y":-2,"z":0,"value":0.2670952},{"x":-4,"y":-3,"z":-4,"value":0.33443788},{"x":4,"y":-2,"z":1,"value":0.2996106},{"x":-4,"y":-3,"z":-3,"value":0.15131497},{"x":4,"y":-2,"z":2,"value":0.32506022},{"x":4,"y":-2,"z":3,"value":0.26021045},{"x":2,"y":-2,"z":-6,"value":0.14228141},{"x":2,"y":-2,"z":-5,"value":0.28900933},{"x":-4,"y":-3,"z":1,"value":0.067771114},{"x":2,"y":-2,"z":-3,"value":0.052811366},{"x":-4,"y":-3,"z":2,"value":0.17757142},{"x":2,"y":-2,"z":-2,"value":0.07007337},{"x":-4,"y":-3,"z":3,"value":0.43620273},{"x":2,"y":-2,"z":-1,"value":0.045571856},{"x":2,"y":-2,"z":0,"value":0.04191669},{"x":2,"y":-2,"z":1,"value":0.049822517},{"x":0,"y":-2,"z":-6,"value":0.2575168},{"x":-6,"y":-3,"z":-2,"value":0.027247},{"x":2,"y":-2,"z":3,"value":0.21637604},{"x":0,"y":-2,"z":-5,"value":0.22608729},{"x":-6,"y":-3,"z":-1,"value":0.052239742},{"x":2,"y":-2,"z":4,"value":0.111043945},{"x":0,"y":-2,"z":-4,"value":0.012464866},{"x":-6,"y":-3,"z":0,"value":0.04866333},{"x":0,"y":-2,"z":-3,"value":0.06670999},{"x":-6,"y":-3,"z":1,"value":0.015866054},{"x":0,"y":-2,"z":-2,"value":0.30926186},{"x":0,"y":-2,"z":-1,"value":0.15524076},{"x":0,"y":-2,"z":0,"value":0.1818783},{"x":0,"y":-2,"z":1,"value":0.11035408},{"x":0,"y":-2,"z":3,"value":0.22883502},{"x":-2,"y":-2,"z":-6,"value":0.17714584},{"x":0,"y":-2,"z":4,"value":0.19961827},{"x":-2,"y":-2,"z":-5,"value":0.2624752},{"x":-2,"y":-2,"z":-3,"value":0.1631592},{"x":-2,"y":-2,"z":-2,"value":0.2006068},{"x":-2,"y":-2,"z":-1,"value":0.32309604},{"x":4,"y":-1,"z":-5,"value":0.20530376},{"x":-2,"y":-2,"z":0,"value":0.2788199},{"x":4,"y":-1,"z":-4,"value":0.3460351},{"x":-2,"y":-2,"z":1,"value":0.167276},{"x":4,"y":-1,"z":-3,"value":0.29152042},{"x":-2,"y":-2,"z":2,"value":0.010184899},{"x":4,"y":-1,"z":-2,"value":0.26849893},{"x":-2,"y":-2,"z":3,"value":0.23547888},{"x":4,"y":-1,"z":-1,"value":0.22393928},{"x":-2,"y":-2,"z":4,"value":0.23647222},{"x":-4,"y":-2,"z":-5,"value":0.31140032},{"x":4,"y":-1,"z":0,"value":0.23075897},{"x":-4,"y":-2,"z":-4,"value":0.26383504},{"x":4,"y":-1,"z":1,"value":0.28333443},{"x":-4,"y":-2,"z":-3,"value":0.074632764},{"x":4,"y":-1,"z":2,"value":0.3052432},{"x":4,"y":-1,"z":3,"value":0.3167842},{"x":2,"y":-1,"z":-6,"value":0.2019352},{"x":-4,"y":-2,"z":-1,"value":0.095368795},{"x":2,"y":-1,"z":-5,"value":0.24460217},{"x":-4,"y":-2,"z":0,"value":0.048790075},{"x":2,"y":-1,"z":-3,"value":0.051493578},{"x":-4,"y":-2,"z":2,"value":0.031456806},{"x":2,"y":-1,"z":-2,"value":0.035463378},{"x":-4,"y":-2,"z":3,"value":0.40974584},{"x":2,"y":-1,"z":-1,"value":0.117280215},{"x":-4,"y":-2,"z":4,"value":0.066794775},{"x":2,"y":-1,"z":1,"value":0.025745623},{"x":-6,"y":-2,"z":-3,"value":0.015367508},{"x":0,"y":-1,"z":-6,"value":0.26517975},{"x":-6,"y":-2,"z":-2,"value":0.088196084},{"x":2,"y":-1,"z":3,"value":0.20446378},{"x":0,"y":-1,"z":-5,"value":0.16444024},{"x":-6,"y":-2,"z":-1,"value":0.14444664},{"x":2,"y":-1,"z":4,"value":0.14408502},{"x":0,"y":-1,"z":-4,"value":0.06568938},{"x":-6,"y":-2,"z":0,"value":0.13905454},{"x":0,"y":-1,"z":-3,"value":0.096654914},{"x":-6,"y":-2,"z":1,"value":0.07560326},{"x":0,"y":-1,"z":-2,"value":0.16360947},{"x":-6,"y":-2,"z":2,"value":0.010286438},{"x":0,"y":-1,"z":1,"value":0.2134677},{"x":0,"y":-1,"z":2,"value":0.21398449},{"x":0,"y":-1,"z":3,"value":0.20785928},{"x":-2,"y":-1,"z":-6,"value":0.20926228},{"x":0,"y":-1,"z":4,"value":0.21685117},{"x":-2,"y":-1,"z":-5,"value":0.24494755},{"x":-2,"y":-1,"z":-3,"value":0.051797993},{"x":-2,"y":-1,"z":-2,"value":0.23653641},{"x":-2,"y":-1,"z":-1,"value":0.06860194},{"x":4,"y":0,"z":-5,"value":0.22387496},{"x":-2,"y":-1,"z":0,"value":0.29414675},{"x":4,"y":0,"z":-4,"value":0.33155346},{"x":-2,"y":-1,"z":1,"value":0.29104018},{"x":4,"y":0,"z":-3,"value":0.29253817},{"x":4,"y":0,"z":-2,"value":0.26859868},{"x":-2,"y":-1,"z":3,"value":0.27381086},{"x":4,"y":0,"z":-1,"value":0.22114763},{"x":-2,"y":-1,"z":4,"value":0.21763164},{"x":-4,"y":-1,"z":-5,"value":0.33911943},{"x":4,"y":0,"z":0,"value":0.23879248},{"x":-4,"y":-1,"z":-4,"value":0.20713817},{"x":4,"y":0,"z":1,"value":0.26119152},{"x":-4,"y":-1,"z":-3,"value":0.06445278},{"x":4,"y":0,"z":2,"value":0.31140736},{"x":-4,"y":-1,"z":-2,"value":0.049899362},{"x":4,"y":0,"z":3,"value":0.3162303},{"x":2,"y":0,"z":-6,"value":0.20847574},{"x":-4,"y":-1,"z":-1,"value":0.032244734},{"x":2,"y":0,"z":-5,"value":0.22483778},{"x":-4,"y":-1,"z":0,"value":0.07985089},{"x":2,"y":0,"z":-3,"value":0.060841523},{"x":2,"y":0,"z":-2,"value":0.06398755},{"x":-4,"y":-1,"z":3,"value":0.39131084},{"x":-4,"y":-1,"z":4,"value":0.14439046},{"x":2,"y":0,"z":1,"value":0.022390611},{"x":-6,"y":-1,"z":-3,"value":0.03792721},{"x":2,"y":0,"z":2,"value":0.022689618},{"x":0,"y":0,"z":-6,"value":0.28766388},{"x":-6,"y":-1,"z":-2,"value":0.119543284},{"x":2,"y":0,"z":3,"value":0.167264},{"x":0,"y":0,"z":-5,"value":0.19595227},{"x":-6,"y":-1,"z":-1,"value":0.17053999},{"x":2,"y":0,"z":4,"value":0.1502006},{"x":-6,"y":-1,"z":0,"value":0.16820073},{"x":0,"y":0,"z":-3,"value":0.289406},{"x":-6,"y":-1,"z":1,"value":0.113989644},{"x":0,"y":0,"z":-2,"value":0.043890588},{"x":-6,"y":-1,"z":2,"value":0.03776157},{"x":0,"y":0,"z":0,"value":0.0353716},{"x":0,"y":0,"z":1,"value":0.1650196},{"x":0,"y":0,"z":3,"value":0.2767108},{"x":-2,"y":0,"z":-6,"value":0.23582056},{"x":0,"y":0,"z":4,"value":0.20701945},{"x":-2,"y":0,"z":-5,"value":0.22279269},{"x":-2,"y":0,"z":-3,"value":0.21952236},{"x":-2,"y":0,"z":-2,"value":0.22204664},{"x":-2,"y":0,"z":-1,"value":0.15713137},{"x":4,"y":1,"z":-5,"value":0.1571049},{"x":-2,"y":0,"z":0,"value":0.15748715},{"x":4,"y":1,"z":-4,"value":0.3500187},{"x":-2,"y":0,"z":1,"value":0.28655645},{"x":4,"y":1,"z":-3,"value":0.3069947},{"x":4,"y":1,"z":-2,"value":0.30876082},{"x":-2,"y":0,"z":3,"value":0.3280689},{"x":4,"y":1,"z":-1,"value":0.25127965},{"x":-4,"y":0,"z":-5,"value":0.35079673},{"x":-2,"y":0,"z":4,"value":0.18453833},{"x":4,"y":1,"z":0,"value":0.2478262},{"x":-4,"y":0,"z":-4,"value":0.19489707},{"x":4,"y":1,"z":1,"value":0.26022077},{"x":-4,"y":0,"z":-3,"value":0.052071624},{"x":4,"y":1,"z":2,"value":0.31718004},{"x":-4,"y":0,"z":-2,"value":0.05517038},{"x":4,"y":1,"z":3,"value":0.2788378},{"x":2,"y":1,"z":-6,"value":0.17513084},{"x":2,"y":1,"z":-5,"value":0.2518212},{"x":-4,"y":0,"z":0,"value":0.124419756},{"x":-4,"y":0,"z":1,"value":0.14014232},{"x":2,"y":1,"z":-3,"value":0.061135896},{"x":2,"y":1,"z":-2,"value":0.06456962},{"x":-4,"y":0,"z":3,"value":0.40184075},{"x":2,"y":1,"z":-1,"value":0.023843981},{"x":-4,"y":0,"z":4,"value":0.14929298},{"x":2,"y":1,"z":0,"value":0.017472982},{"x":2,"y":1,"z":1,"value":0.05998461},{"x":-6,"y":0,"z":-3,"value":0.035770547},{"x":0,"y":1,"z":-6,"value":0.26270837},{"x":-6,"y":0,"z":-2,"value":0.10685861},{"x":2,"y":1,"z":3,"value":0.122833855},{"x":0,"y":1,"z":-5,"value":0.18948413},{"x":-6,"y":0,"z":-1,"value":0.14031893},{"x":2,"y":1,"z":4,"value":0.15380496},{"x":0,"y":1,"z":-4,"value":0.0125099495},{"x":-6,"y":0,"z":0,"value":0.14049013},{"x":0,"y":1,"z":-3,"value":0.114147484},{"x":-6,"y":0,"z":1,"value":0.10371459},{"x":0,"y":1,"z":-2,"value":0.28834537},{"x":-6,"y":0,"z":2,"value":0.039461758},{"x":0,"y":1,"z":-1,"value":0.11110479},{"x":0,"y":1,"z":0,"value":0.10519007},{"x":0,"y":1,"z":1,"value":0.15953621},{"x":0,"y":1,"z":3,"value":0.2515858},{"x":-2,"y":1,"z":-6,"value":0.20483994},{"x":0,"y":1,"z":4,"value":0.16382809},{"x":-2,"y":1,"z":-5,"value":0.2517565},{"x":-2,"y":1,"z":-3,"value":0.07598784},{"x":-2,"y":1,"z":-2,"value":0.22949776},{"x":-2,"y":1,"z":-1,"value":0.2218897},{"x":4,"y":2,"z":-5,"value":0.021135641},{"x":-2,"y":1,"z":0,"value":0.40332836},{"x":4,"y":2,"z":-4,"value":0.33487648},{"x":-2,"y":1,"z":1,"value":0.2337729},{"x":4,"y":2,"z":-3,"value":0.34376958},{"x":4,"y":2,"z":-2,"value":0.31118357},{"x":-2,"y":1,"z":3,"value":0.30121106},{"x":4,"y":2,"z":-1,"value":0.29963037},{"x":-4,"y":1,"z":-5,"value":0.33587292},{"x":-2,"y":1,"z":4,"value":0.1477059},{"x":4,"y":2,"z":0,"value":0.31251594},{"x":-4,"y":1,"z":-4,"value":0.24505478},{"x":4,"y":2,"z":1,"value":0.32258555},{"x":-4,"y":1,"z":-3,"value":0.053862102},{"x":4,"y":2,"z":2,"value":0.33882102},{"x":-4,"y":1,"z":-2,"value":0.0639364},{"x":4,"y":2,"z":3,"value":0.17661983},{"x":2,"y":2,"z":-6,"value":0.0528929},{"x":-4,"y":1,"z":-1,"value":0.040943146},{"x":2,"y":2,"z":-5,"value":0.35223797},{"x":-4,"y":1,"z":0,"value":0.096499436},{"x":-4,"y":1,"z":1,"value":0.036138877},{"x":2,"y":2,"z":-2,"value":0.02853892},{"x":-4,"y":1,"z":3,"value":0.44345626},{"x":2,"y":2,"z":-1,"value":0.020970426},{"x":-4,"y":1,"z":4,"value":0.106140584},{"x":2,"y":2,"z":0,"value":0.023888946},{"x":2,"y":2,"z":1,"value":0.026603006},{"x":-6,"y":1,"z":-3,"value":0.010986901},{"x":0,"y":2,"z":-6,"value":0.1948765},{"x":-6,"y":1,"z":-2,"value":0.060314037},{"x":2,"y":2,"z":3,"value":0.20446372},{"x":0,"y":2,"z":-5,"value":0.23152262},{"x":-6,"y":1,"z":-1,"value":0.10896334},{"x":2,"y":2,"z":4,"value":0.11708769},{"x":-6,"y":1,"z":0,"value":0.10594484},{"x":0,"y":2,"z":-3,"value":0.034748144},{"x":-6,"y":1,"z":1,"value":0.05766461},{"x":-6,"y":1,"z":2,"value":0.020418406},{"x":0,"y":2,"z":0,"value":0.25592336},{"x":0,"y":2,"z":1,"value":0.02000799},{"x":0,"y":2,"z":2,"value":0.060867317},{"x":0,"y":2,"z":3,"value":0.16012515},{"x":-2,"y":2,"z":-6,"value":0.079428054},{"x":0,"y":2,"z":4,"value":0.16660628},{"x":-2,"y":2,"z":-5,"value":0.3017062},{"x":-2,"y":2,"z":-3,"value":0.0706383},{"x":-2,"y":2,"z":-2,"value":0.1023559},{"x":-2,"y":2,"z":-1,"value":0.092346735},{"x":-2,"y":2,"z":0,"value":0.06236676},{"x":4,"y":3,"z":-4,"value":0.057834543},{"x":-2,"y":2,"z":1,"value":0.040021412},{"x":4,"y":3,"z":-3,"value":0.2728798},{"x":4,"y":3,"z":-2,"value":0.3353462},{"x":-2,"y":2,"z":3,"value":0.22212735},{"x":4,"y":3,"z":-1,"value":0.33574098},{"x":-2,"y":2,"z":4,"value":0.12578788},{"x":-4,"y":2,"z":-5,"value":0.21869251},{"x":4,"y":3,"z":0,"value":0.3210838},{"x":-4,"y":2,"z":-4,"value":0.33082014},{"x":4,"y":3,"z":1,"value":0.30774045},{"x":-4,"y":2,"z":-3,"value":0.13629535},{"x":4,"y":3,"z":2,"value":0.21361017},{"x":-4,"y":2,"z":-2,"value":0.022997864},{"x":2,"y":3,"z":-5,"value":0.34811687},{"x":2,"y":3,"z":-4,"value":0.28375423},{"x":2,"y":3,"z":-3,"value":0.09439933},{"x":2,"y":3,"z":-2,"value":0.018877417},{"x":-4,"y":2,"z":3,"value":0.51257455},{"x":-4,"y":2,"z":4,"value":0.039139546},{"x":2,"y":3,"z":2,"value":0.08454387},{"x":0,"y":3,"z":-6,"value":0.021461094},{"x":-6,"y":2,"z":-2,"value":0.019000137},{"x":2,"y":3,"z":3,"value":0.46491763},{"x":0,"y":3,"z":-5,"value":0.37668318},{"x":-6,"y":2,"z":-1,"value":0.042648923},{"x":0,"y":3,"z":-4,"value":0.13877779},{"x":-6,"y":2,"z":0,"value":0.04236343},{"x":0,"y":3,"z":-3,"value":0.03634531},{"x":-6,"y":2,"z":1,"value":0.021488512},{"x":0,"y":3,"z":-2,"value":0.087373435},{"x":0,"y":3,"z":-1,"value":0.057755962},{"x":0,"y":3,"z":0,"value":0.052908443},{"x":0,"y":3,"z":1,"value":0.05874742},{"x":0,"y":3,"z":3,"value":0.43846536},{"x":0,"y":3,"z":4,"value":0.05404228},{"x":-2,"y":3,"z":-5,"value":0.3754919},{"x":-2,"y":3,"z":-4,"value":0.21189772},{"x":-2,"y":3,"z":-1,"value":0.014270544},{"x":-2,"y":3,"z":0,"value":0.014329337},{"x":-2,"y":3,"z":1,"value":0.07333052},{"x":4,"y":4,"z":-2,"value":0.02583822},{"x":-2,"y":3,"z":3,"value":0.42686385},{"x":4,"y":4,"z":-1,"value":0.05703075},{"x":-2,"y":3,"z":4,"value":0.045568373},{"x":-4,"y":3,"z":-5,"value":0.018204987},{"x":4,"y":4,"z":0,"value":0.05332495},{"x":-4,"y":3,"z":-4,"value":0.35608608},{"x":4,"y":4,"z":1,"value":0.0119673135},{"x":-4,"y":3,"z":-3,"value":0.3178662},{"x":-4,"y":3,"z":-2,"value":0.22590545},{"x":-4,"y":3,"z":-1,"value":0.19733766},{"x":-4,"y":3,"z":0,"value":0.23843202},{"x":2,"y":4,"z":-4,"value":0.22853738},{"x":-4,"y":3,"z":1,"value":0.29983002},{"x":2,"y":4,"z":-3,"value":0.3358419},{"x":-4,"y":3,"z":2,"value":0.38481078},{"x":2,"y":4,"z":-2,"value":0.31777215},{"x":-4,"y":3,"z":3,"value":0.45807353},{"x":2,"y":4,"z":-1,"value":0.3060303},{"x":2,"y":4,"z":0,"value":0.3101191},{"x":2,"y":4,"z":1,"value":0.33080396},{"x":2,"y":4,"z":2,"value":0.3302498},{"x":2,"y":4,"z":3,"value":0.10472761},{"x":0,"y":4,"z":-5,"value":0.13932332},{"x":0,"y":4,"z":-4,"value":0.32283953},{"x":0,"y":4,"z":-3,"value":0.30716476},{"x":0,"y":4,"z":-2,"value":0.2610706},{"x":0,"y":4,"z":-1,"value":0.24136141},{"x":0,"y":4,"z":0,"value":0.26030394},{"x":0,"y":4,"z":1,"value":0.2845012},{"x":0,"y":4,"z":2,"value":0.31612962},{"x":0,"y":4,"z":3,"value":0.28165242},{"x":-2,"y":4,"z":-5,"value":0.06697746},{"x":-2,"y":4,"z":-4,"value":0.35494733},{"x":-2,"y":4,"z":-3,"value":0.31577593},{"x":-2,"y":4,"z":-2,"value":0.2812192},{"x":-2,"y":4,"z":-1,"value":0.29226032},{"x":-2,"y":4,"z":0,"value":0.27196005},{"x":-2,"y":4,"z":1,"value":0.29366633},{"x":-2,"y":4,"z":2,"value":0.33279267},{"x":-2,"y":4,"z":3,"value":0.2846615},{"x":-4,"y":4,"z":-4,"value":0.02547121},{"x":-4,"y":4,"z":-3,"value":0.25373676},{"x":-4,"y":4,"z":-2,"value":0.36673504},{"x":-4,"y":4,"z":-1,"value":0.36835724},{"x":-4,"y":4,"z":0,"value":0.35016608},{"x":-4,"y":4,"z":1,"value":0.3391745},{"x":-4,"y":4,"z":2,"value":0.25903374},{"x":-4,"y":4,"z":3,"value":0.020218348},{"x":2,"y":5,"z":-1,"value":0.024086034},{"x":2,"y":5,"z":0,"value":0.020375347},{"x":0,"y":5,"z":-3,"value":0.049463104},{"x":0,"y":5,"z":-2,"value":0.109388575},{"x":0,"y":5,"z":-1,"value":0.118748814},{"x":0,"y":5,"z":0,"value":0.102255106},{"x":0,"y":5,"z":1,"value":0.0564317},{"x":-2,"y":5,"z":-3,"value":0.044482317},{"x":-2,"y":5,"z":-2,"value":0.13232365},{"x":-2,"y":5,"z":-1,"value":0.17893943},{"x":-2,"y":5,"z":0,"value":0.14944348},{"x":-2,"y":5,"z":1,"value":0.08896859},{"x":-2,"y":5,"z":2,"value":0.013669836},{"x":1,"y":-6,"z":-3,"value":0.052476216},{"x":1,"y":-6,"z":-2,"value":0.1397783},{"x":1,"y":-6,"z":-1,"value":0.17346674},{"x":1,"y":-6,"z":0,"value":0.16546834},{"x":1,"y":-6,"z":1,"value":0.08905817},{"x":-1,"y":-6,"z":-3,"value":0.13733627},{"x":-1,"y":-6,"z":-2,"value":0.25631067},{"x":-1,"y":-6,"z":-1,"value":0.30397436},{"x":-1,"y":-6,"z":0,"value":0.25820488},{"x":-1,"y":-6,"z":1,"value":0.17644432},{"x":-1,"y":-6,"z":2,"value":0.035280775},{"x":-3,"y":-6,"z":-2,"value":0.076555446},{"x":-3,"y":-6,"z":-1,"value":0.15550819},{"x":-3,"y":-6,"z":0,"value":0.121190384},{"x":3,"y":-5,"z":-4,"value":0.03221593},{"x":-3,"y":-6,"z":1,"value":0.039598703},{"x":3,"y":-5,"z":-3,"value":0.23259963},{"x":3,"y":-5,"z":-2,"value":0.32269272},{"x":3,"y":-5,"z":-1,"value":0.3280055},{"x":3,"y":-5,"z":0,"value":0.3309711},{"x":3,"y":-5,"z":1,"value":0.31225595},{"x":3,"y":-5,"z":2,"value":0.1485775},{"x":1,"y":-5,"z":-5,"value":0.05970036},{"x":1,"y":-5,"z":-4,"value":0.34003818},{"x":1,"y":-5,"z":-3,"value":0.31468365},{"x":1,"y":-5,"z":-2,"value":0.26860538},{"x":1,"y":-5,"z":-1,"value":0.25134844},{"x":1,"y":-5,"z":0,"value":0.25542971},{"x":1,"y":-5,"z":1,"value":0.29879177},{"x":1,"y":-5,"z":2,"value":0.34016308},{"x":1,"y":-5,"z":3,"value":0.22341174},{"x":-1,"y":-5,"z":-5,"value":0.12843764},{"x":-1,"y":-5,"z":-4,"value":0.35824555},{"x":-1,"y":-5,"z":-3,"value":0.27162617},{"x":-1,"y":-5,"z":-2,"value":0.23183188},{"x":-1,"y":-5,"z":-1,"value":0.2140795},{"x":-1,"y":-5,"z":0,"value":0.21839564},{"x":-1,"y":-5,"z":1,"value":0.26299852},{"x":-1,"y":-5,"z":2,"value":0.30739757},{"x":-1,"y":-5,"z":3,"value":0.30893573},{"x":-3,"y":-5,"z":-4,"value":0.27609307},{"x":-3,"y":-5,"z":-3,"value":0.38394392},{"x":-3,"y":-5,"z":-2,"value":0.3004161},{"x":-3,"y":-5,"z":-1,"value":0.26360855},{"x":3,"y":-4,"z":-5,"value":0.050382257},{"x":-3,"y":-5,"z":0,"value":0.2859702},{"x":3,"y":-4,"z":-4,"value":0.3667993},{"x":-3,"y":-5,"z":1,"value":0.34348065},{"x":3,"y":-4,"z":-3,"value":0.34355658},{"x":-3,"y":-5,"z":2,"value":0.35545},{"x":3,"y":-4,"z":-2,"value":0.24567634},{"x":-3,"y":-5,"z":3,"value":0.061047744},{"x":3,"y":-4,"z":-1,"value":0.22379093},{"x":3,"y":-4,"z":0,"value":0.2279728},{"x":3,"y":-4,"z":1,"value":0.27997932},{"x":3,"y":-4,"z":2,"value":0.41144413},{"x":-5,"y":-5,"z":-2,"value":0.0460243},{"x":3,"y":-4,"z":3,"value":0.2744155},{"x":1,"y":-4,"z":-5,"value":0.35634536},{"x":-5,"y":-5,"z":-1,"value":0.07691548},{"x":1,"y":-4,"z":-4,"value":0.2031934},{"x":-5,"y":-5,"z":0,"value":0.067537405},{"x":1,"y":-4,"z":-3,"value":0.024782874},{"x":1,"y":-4,"z":-2,"value":0.032250434},{"x":1,"y":-4,"z":-1,"value":0.07655195},{"x":1,"y":-4,"z":0,"value":0.070716575},{"x":1,"y":-4,"z":2,"value":0.08587252},{"x":1,"y":-4,"z":3,"value":0.39985302},{"x":1,"y":-4,"z":4,"value":0.017065013},{"x":-1,"y":-4,"z":-5,"value":0.3499141},{"x":-1,"y":-4,"z":-4,"value":0.15240262},{"x":-1,"y":-4,"z":-2,"value":0.013764188},{"x":-1,"y":-4,"z":-1,"value":0.0636105},{"x":-1,"y":-4,"z":0,"value":0.03533984},{"x":-1,"y":-4,"z":2,"value":0.061082684},{"x":5,"y":-3,"z":-2,"value":0.041106116},{"x":-1,"y":-4,"z":3,"value":0.35149667},{"x":5,"y":-3,"z":-1,"value":0.049500097},{"x":-1,"y":-4,"z":4,"value":0.04612441},{"x":-3,"y":-4,"z":-5,"value":0.23184043},{"x":5,"y":-3,"z":0,"value":0.03922795},{"x":-3,"y":-4,"z":-4,"value":0.3138012},{"x":-3,"y":-4,"z":-3,"value":0.08892428},{"x":3,"y":-3,"z":-5,"value":0.31196478},{"x":3,"y":-3,"z":-4,"value":0.30221343},{"x":-3,"y":-4,"z":1,"value":0.048558988},{"x":3,"y":-3,"z":-3,"value":0.06504684},{"x":-3,"y":-4,"z":2,"value":0.16561756},{"x":-3,"y":-4,"z":3,"value":0.41394234},{"x":3,"y":-3,"z":0,"value":0.022175126},{"x":-5,"y":-4,"z":-3,"value":0.21801752},{"x":3,"y":-3,"z":2,"value":0.15931052},{"x":1,"y":-3,"z":-6,"value":0.11672416},{"x":3,"y":-3,"z":3,"value":0.4568564},{"x":-5,"y":-4,"z":-2,"value":0.3265256},{"x":1,"y":-3,"z":-5,"value":0.2955904},{"x":-5,"y":-4,"z":-1,"value":0.33114776},{"x":-5,"y":-4,"z":0,"value":0.3364194},{"x":1,"y":-3,"z":-3,"value":0.028045319},{"x":-5,"y":-4,"z":1,"value":0.31449452},{"x":1,"y":-3,"z":-2,"value":0.10771348},{"x":-5,"y":-4,"z":2,"value":0.13645084},{"x":1,"y":-3,"z":-1,"value":0.048758827},{"x":1,"y":-3,"z":0,"value":0.13480633},{"x":1,"y":-3,"z":1,"value":0.04853546},{"x":1,"y":-3,"z":3,"value":0.25339594},{"x":-1,"y":-3,"z":-6,"value":0.14487764},{"x":1,"y":-3,"z":4,"value":0.113355756},{"x":-1,"y":-3,"z":-5,"value":0.27426726},{"x":-1,"y":-3,"z":-3,"value":0.03762094},{"x":-1,"y":-3,"z":-2,"value":0.08180031},{"x":-1,"y":-3,"z":-1,"value":0.12550579},{"x":-1,"y":-3,"z":0,"value":0.19782932},{"x":-1,"y":-3,"z":1,"value":0.053196333},{"x":5,"y":-2,"z":-3,"value":0.04516405},{"x":5,"y":-2,"z":-2,"value":0.10655637},{"x":-1,"y":-3,"z":3,"value":0.2093277},{"x":5,"y":-2,"z":-1,"value":0.10108148},{"x":-1,"y":-3,"z":4,"value":0.19346122},{"x":-3,"y":-3,"z":-5,"value":0.36914456},{"x":5,"y":-2,"z":0,"value":0.07211572},{"x":-3,"y":-3,"z":-4,"value":0.11829581},{"x":5,"y":-2,"z":1,"value":0.03976233},{"x":-3,"y":-3,"z":-2,"value":0.0768804},{"x":-3,"y":-3,"z":-1,"value":0.04600566},{"x":3,"y":-2,"z":-5,"value":0.37636492},{"x":-3,"y":-3,"z":0,"value":0.07791377},{"x":3,"y":-2,"z":-4,"value":0.17994079},{"x":-3,"y":-3,"z":1,"value":0.02756191},{"x":3,"y":-2,"z":-2,"value":0.07078186},{"x":-3,"y":-3,"z":3,"value":0.31691313},{"x":3,"y":-2,"z":-1,"value":0.01238624},{"x":-3,"y":-3,"z":4,"value":0.104463235},{"x":3,"y":-2,"z":0,"value":0.07844045},{"x":-5,"y":-3,"z":-4,"value":0.1698741},{"x":-5,"y":-3,"z":-3,"value":0.34536085},{"x":3,"y":-2,"z":2,"value":0.08350444},{"x":1,"y":-2,"z":-6,"value":0.24342772},{"x":-5,"y":-3,"z":-2,"value":0.32698178},{"x":3,"y":-2,"z":3,"value":0.40025046},{"x":1,"y":-2,"z":-5,"value":0.23124868},{"x":-5,"y":-3,"z":-1,"value":0.31526238},{"x":3,"y":-2,"z":4,"value":0.025675058},{"x":-5,"y":-3,"z":0,"value":0.31187505},{"x":1,"y":-2,"z":-3,"value":0.08487791},{"x":-5,"y":-3,"z":1,"value":0.33322427},{"x":1,"y":-2,"z":-2,"value":0.21086185},{"x":-5,"y":-3,"z":2,"value":0.3567444},{"x":1,"y":-2,"z":-1,"value":0.18418601},{"x":-5,"y":-3,"z":3,"value":0.10166172},{"x":1,"y":-2,"z":0,"value":0.40947628},{"x":1,"y":-2,"z":1,"value":0.12726705},{"x":1,"y":-2,"z":3,"value":0.26773605},{"x":-1,"y":-2,"z":-6,"value":0.24172375},{"x":1,"y":-2,"z":4,"value":0.1436935},{"x":-1,"y":-2,"z":-5,"value":0.23304592},{"x":-1,"y":-2,"z":-4,"value":0.028580584},{"x":-1,"y":-2,"z":-3,"value":0.061136},{"x":-1,"y":-2,"z":-2,"value":0.2932464},{"x":-1,"y":-2,"z":-1,"value":0.13010162},{"x":-1,"y":-2,"z":0,"value":0.18134049},{"x":-1,"y":-2,"z":1,"value":0.13537723},{"x":5,"y":-1,"z":-3,"value":0.07251336},{"x":-1,"y":-2,"z":2,"value":0.10324188},{"x":5,"y":-1,"z":-2,"value":0.105220124},{"x":-1,"y":-2,"z":3,"value":0.23530832},{"x":-3,"y":-2,"z":-6,"value":0.047682572},{"x":5,"y":-1,"z":-1,"value":0.07645953},{"x":-1,"y":-2,"z":4,"value":0.23005131},{"x":-3,"y":-2,"z":-5,"value":0.32190382},{"x":5,"y":-1,"z":0,"value":0.048608493},{"x":-3,"y":-2,"z":-4,"value":0.03550072},{"x":5,"y":-1,"z":1,"value":0.04085585},{"x":-3,"y":-2,"z":-3,"value":0.0237877},{"x":-3,"y":-2,"z":-2,"value":0.05378253},{"x":3,"y":-1,"z":-6,"value":0.031788874},{"x":-3,"y":-2,"z":-1,"value":0.05665902},{"x":3,"y":-1,"z":-5,"value":0.36059535},{"x":-3,"y":-2,"z":0,"value":0.054386742},{"x":3,"y":-1,"z":-4,"value":0.09510755},{"x":-3,"y":-2,"z":1,"value":0.0565395},{"x":3,"y":-1,"z":-3,"value":0.019883722},{"x":3,"y":-1,"z":-2,"value":0.022829264},{"x":-3,"y":-2,"z":3,"value":0.18622711},{"x":-3,"y":-2,"z":4,"value":0.22178853},{"x":3,"y":-1,"z":0,"value":0.23359007},{"x":-5,"y":-2,"z":-4,"value":0.26936236},{"x":-5,"y":-2,"z":-3,"value":0.3203953},{"x":3,"y":-1,"z":2,"value":0.054261327},{"x":1,"y":-1,"z":-6,"value":0.26007223},{"x":-5,"y":-2,"z":-2,"value":0.2965377},{"x":3,"y":-1,"z":3,"value":0.3896818},{"x":1,"y":-1,"z":-5,"value":0.16792813},{"x":-5,"y":-2,"z":-1,"value":0.2717718},{"x":3,"y":-1,"z":4,"value":0.047490776},{"x":1,"y":-1,"z":-4,"value":0.06634877},{"x":-5,"y":-2,"z":0,"value":0.2632397},{"x":1,"y":-1,"z":-3,"value":0.17842925},{"x":-5,"y":-2,"z":1,"value":0.289217},{"x":1,"y":-1,"z":-2,"value":0.24233368},{"x":-5,"y":-2,"z":2,"value":0.32723758},{"x":1,"y":-1,"z":-1,"value":0.1931053},{"x":-5,"y":-2,"z":3,"value":0.31760684},{"x":1,"y":-1,"z":0,"value":0.17372343},{"x":1,"y":-1,"z":1,"value":0.28374925},{"x":1,"y":-1,"z":3,"value":0.27767614},{"x":-1,"y":-1,"z":-6,"value":0.24633782},{"x":1,"y":-1,"z":4,"value":0.16050434},{"x":-1,"y":-1,"z":-5,"value":0.18613645},{"x":-1,"y":-1,"z":-4,"value":0.0385203},{"x":-1,"y":-1,"z":-3,"value":0.09109182},{"x":-1,"y":-1,"z":-2,"value":0.110293366},{"x":-1,"y":-1,"z":0,"value":0.16524053},{"x":5,"y":0,"z":-3,"value":0.0696979},{"x":5,"y":0,"z":-2,"value":0.09248563},{"x":-3,"y":-1,"z":-6,"value":0.075071946},{"x":-1,"y":-1,"z":3,"value":0.22841986},{"x":5,"y":0,"z":-1,"value":0.049104895},{"x":-3,"y":-1,"z":-5,"value":0.2970936},{"x":-1,"y":-1,"z":4,"value":0.2291914},{"x":5,"y":0,"z":0,"value":0.0402248},{"x":-3,"y":-1,"z":-4,"value":0.020418465},{"x":5,"y":0,"z":1,"value":0.034926604},{"x":-3,"y":-1,"z":-3,"value":0.01996538},{"x":-3,"y":-1,"z":-2,"value":0.04747931},{"x":3,"y":0,"z":-6,"value":0.038743198},{"x":-3,"y":-1,"z":-1,"value":0.016370654},{"x":3,"y":0,"z":-5,"value":0.36961463},{"x":-3,"y":-1,"z":0,"value":0.01763358},{"x":3,"y":0,"z":-4,"value":0.08657362},{"x":-3,"y":-1,"z":1,"value":0.046329267},{"x":3,"y":0,"z":-3,"value":0.012114592},{"x":-3,"y":-1,"z":2,"value":0.01038228},{"x":3,"y":0,"z":-2,"value":0.11779121},{"x":-3,"y":-1,"z":3,"value":0.13008064},{"x":3,"y":0,"z":-1,"value":0.14043349},{"x":-3,"y":-1,"z":4,"value":0.23636335},{"x":-5,"y":-1,"z":-5,"value":0.042966712},{"x":3,"y":0,"z":0,"value":0.28684688},{"x":-5,"y":-1,"z":-4,"value":0.30379155},{"x":3,"y":0,"z":1,"value":0.052653395},{"x":-5,"y":-1,"z":-3,"value":0.31517485},{"x":3,"y":0,"z":2,"value":0.022675127},{"x":1,"y":0,"z":-6,"value":0.2591121},{"x":-5,"y":-1,"z":-2,"value":0.26550698},{"x":3,"y":0,"z":3,"value":0.41430548},{"x":1,"y":0,"z":-5,"value":0.18153933},{"x":-5,"y":-1,"z":-1,"value":0.24932146},{"x":3,"y":0,"z":4,"value":0.052202117},{"x":-5,"y":-1,"z":0,"value":0.27841607},{"x":1,"y":0,"z":-3,"value":0.15974832},{"x":-5,"y":-1,"z":1,"value":0.26542544},{"x":1,"y":0,"z":-2,"value":0.24701717},{"x":-5,"y":-1,"z":2,"value":0.29811016},{"x":1,"y":0,"z":-1,"value":0.17008798},{"x":-5,"y":-1,"z":3,"value":0.36769548},{"x":1,"y":0,"z":0,"value":0.2659537},{"x":1,"y":0,"z":1,"value":0.18695486},{"x":1,"y":0,"z":3,"value":0.30425677},{"x":-1,"y":0,"z":-6,"value":0.27185485},{"x":1,"y":0,"z":4,"value":0.1603804},{"x":-1,"y":0,"z":-5,"value":0.17356262},{"x":-1,"y":0,"z":-4,"value":0.057159655},{"x":-1,"y":0,"z":-3,"value":0.11029934},{"x":-1,"y":0,"z":-2,"value":0.107122965},{"x":-1,"y":0,"z":1,"value":0.12777013},{"x":5,"y":1,"z":-3,"value":0.03917904},{"x":5,"y":1,"z":-2,"value":0.07246891},{"x":-3,"y":0,"z":-6,"value":0.07841458},{"x":-1,"y":0,"z":3,"value":0.2643895},{"x":5,"y":1,"z":-1,"value":0.045912124},{"x":-3,"y":0,"z":-5,"value":0.28180277},{"x":-1,"y":0,"z":4,"value":0.21214917},{"x":5,"y":1,"z":0,"value":0.03712343},{"x":-3,"y":0,"z":-4,"value":0.031640135},{"x":5,"y":1,"z":1,"value":0.02678541},{"x":-3,"y":0,"z":-3,"value":0.019310094},{"x":-3,"y":0,"z":-2,"value":0.02862674},{"x":3,"y":1,"z":-6,"value":0.011136341},{"x":-3,"y":0,"z":-1,"value":0.20161656},{"x":3,"y":1,"z":-5,"value":0.38056737},{"x":3,"y":1,"z":-4,"value":0.150127},{"x":-3,"y":0,"z":1,"value":0.075271696},{"x":-3,"y":0,"z":2,"value":0.010337524},{"x":-3,"y":0,"z":3,"value":0.16943485},{"x":3,"y":1,"z":-1,"value":0.06592701},{"x":-3,"y":0,"z":4,"value":0.21017826},{"x":-5,"y":0,"z":-5,"value":0.044638325},{"x":3,"y":1,"z":0,"value":0.11400611},{"x":-5,"y":0,"z":-4,"value":0.30425853},{"x":-5,"y":0,"z":-3,"value":0.31922892},{"x":3,"y":1,"z":2,"value":0.050385438},{"x":1,"y":1,"z":-6,"value":0.2608949},{"x":-5,"y":0,"z":-2,"value":0.26787612},{"x":3,"y":1,"z":3,"value":0.43962446},{"x":1,"y":1,"z":-5,"value":0.21662244},{"x":-5,"y":0,"z":-1,"value":0.24094164},{"x":3,"y":1,"z":4,"value":0.04285605},{"x":1,"y":1,"z":-4,"value":0.012874231},{"x":-5,"y":0,"z":0,"value":0.24889705},{"x":1,"y":1,"z":-3,"value":0.12008609},{"x":-5,"y":0,"z":1,"value":0.24900988},{"x":1,"y":1,"z":-2,"value":0.38604772},{"x":-5,"y":0,"z":2,"value":0.2883378},{"x":1,"y":1,"z":-1,"value":0.09351781},{"x":-5,"y":0,"z":3,"value":0.36609915},{"x":1,"y":1,"z":0,"value":0.46929413},{"x":1,"y":1,"z":1,"value":0.20895277},{"x":1,"y":1,"z":2,"value":0.012071095},{"x":1,"y":1,"z":3,"value":0.3356052},{"x":-1,"y":1,"z":-6,"value":0.2677236},{"x":1,"y":1,"z":4,"value":0.14717628},{"x":-1,"y":1,"z":-5,"value":0.22046182},{"x":-1,"y":1,"z":-4,"value":0.012194179},{"x":-1,"y":1,"z":-3,"value":0.091496706},{"x":-1,"y":1,"z":-2,"value":0.37364125},{"x":-1,"y":1,"z":-1,"value":0.17527375},{"x":-1,"y":1,"z":0,"value":0.20705983},{"x":-1,"y":1,"z":1,"value":0.16537216},{"x":-1,"y":1,"z":2,"value":0.1709572},{"x":5,"y":2,"z":-2,"value":0.026233708},{"x":-1,"y":1,"z":3,"value":0.22889647},{"x":-3,"y":1,"z":-6,"value":0.057999577},{"x":5,"y":2,"z":-1,"value":0.031573392},{"x":-1,"y":1,"z":4,"value":0.16349033},{"x":-3,"y":1,"z":-5,"value":0.31197876},{"x":5,"y":2,"z":0,"value":0.023987234},{"x":-3,"y":1,"z":-4,"value":0.039078027},{"x":-3,"y":1,"z":-3,"value":0.023349501},{"x":-3,"y":1,"z":-2,"value":0.042441584},{"x":-3,"y":1,"z":-1,"value":0.02717416},{"x":3,"y":2,"z":-5,"value":0.3791201},{"x":-3,"y":1,"z":0,"value":0.02510894},{"x":3,"y":2,"z":-4,"value":0.25953472},{"x":-3,"y":1,"z":1,"value":0.044170693},{"x":3,"y":2,"z":-3,"value":0.084052816},{"x":-3,"y":1,"z":2,"value":0.012592465},{"x":-3,"y":1,"z":3,"value":0.117443815},{"x":-3,"y":1,"z":4,"value":0.1743097},{"x":3,"y":2,"z":0,"value":0.02987814},{"x":-5,"y":1,"z":-4,"value":0.2689343},{"x":-5,"y":1,"z":-3,"value":0.33253786},{"x":3,"y":2,"z":2,"value":0.12472488},{"x":1,"y":2,"z":-6,"value":0.15680516},{"x":-5,"y":1,"z":-2,"value":0.28904122},{"x":3,"y":2,"z":3,"value":0.47230303},{"x":1,"y":2,"z":-5,"value":0.27095073},{"x":-5,"y":1,"z":-1,"value":0.27272978},{"x":3,"y":2,"z":4,"value":0.011749888},{"x":-5,"y":1,"z":0,"value":0.27579054},{"x":1,"y":2,"z":-3,"value":0.027231008},{"x":-5,"y":1,"z":1,"value":0.28092945},{"x":1,"y":2,"z":-2,"value":0.025917351},{"x":-5,"y":1,"z":2,"value":0.31662577},{"x":1,"y":2,"z":-1,"value":0.08653212},{"x":-5,"y":1,"z":3,"value":0.34502962},{"x":1,"y":2,"z":0,"value":0.016276106},{"x":1,"y":2,"z":1,"value":0.03748993},{"x":1,"y":2,"z":3,"value":0.2036145},{"x":-1,"y":2,"z":-6,"value":0.1851176},{"x":1,"y":2,"z":4,"value":0.16450164},{"x":-1,"y":2,"z":-5,"value":0.25076354},{"x":-1,"y":2,"z":-3,"value":0.04426922},{"x":-1,"y":2,"z":-2,"value":0.05091536},{"x":-1,"y":2,"z":-1,"value":0.07164659},{"x":-1,"y":2,"z":1,"value":0.020432591},{"x":-1,"y":2,"z":3,"value":0.20855567},{"x":-1,"y":2,"z":4,"value":0.15169194},{"x":-3,"y":2,"z":-5,"value":0.37777513},{"x":-3,"y":2,"z":-4,"value":0.0983015},{"x":-3,"y":2,"z":-2,"value":0.029041015},{"x":-3,"y":2,"z":-1,"value":0.0381928},{"x":3,"y":3,"z":-5,"value":0.08461937},{"x":-3,"y":2,"z":0,"value":0.13105798},{"x":3,"y":3,"z":-4,"value":0.4042763},{"x":-3,"y":2,"z":1,"value":0.032994613},{"x":3,"y":3,"z":-3,"value":0.33999217},{"x":3,"y":3,"z":-2,"value":0.27945995},{"x":-3,"y":2,"z":3,"value":0.14905286},{"x":3,"y":3,"z":-1,"value":0.24378005},{"x":-3,"y":2,"z":4,"value":0.121982634},{"x":3,"y":3,"z":0,"value":0.28036514},{"x":-5,"y":2,"z":-4,"value":0.1650864},{"x":3,"y":3,"z":1,"value":0.34858635},{"x":-5,"y":2,"z":-3,"value":0.35440668},{"x":3,"y":3,"z":2,"value":0.42139253},{"x":-5,"y":2,"z":-2,"value":0.32785827},{"x":3,"y":3,"z":3,"value":0.4232866},{"x":1,"y":3,"z":-5,"value":0.39389217},{"x":-5,"y":2,"z":-1,"value":0.30689004},{"x":1,"y":3,"z":-4,"value":0.1880618},{"x":-5,"y":2,"z":0,"value":0.30858836},{"x":1,"y":3,"z":-3,"value":0.054209672},{"x":-5,"y":2,"z":1,"value":0.32277024},{"x":1,"y":3,"z":-2,"value":0.08833035},{"x":-5,"y":2,"z":2,"value":0.35489935},{"x":1,"y":3,"z":-1,"value":0.10477986},{"x":-5,"y":2,"z":3,"value":0.23183738},{"x":1,"y":3,"z":0,"value":0.09489624},{"x":1,"y":3,"z":1,"value":0.09277568},{"x":1,"y":3,"z":2,"value":0.03883586},{"x":1,"y":3,"z":3,"value":0.45541248},{"x":-1,"y":3,"z":-6,"value":0.014443576},{"x":1,"y":3,"z":4,"value":0.03892653},{"x":-1,"y":3,"z":-5,"value":0.3677822},{"x":-1,"y":3,"z":-4,"value":0.1592344},{"x":-1,"y":3,"z":-2,"value":0.05765164},{"x":-1,"y":3,"z":-1,"value":0.08350956},{"x":-1,"y":3,"z":0,"value":0.049789436},{"x":-1,"y":3,"z":1,"value":0.09448055},{"x":-1,"y":3,"z":3,"value":0.40858784},{"x":-1,"y":3,"z":4,"value":0.0555066},{"x":-3,"y":3,"z":-5,"value":0.28337646},{"x":-3,"y":3,"z":-4,"value":0.30395582},{"x":-3,"y":3,"z":-3,"value":0.12588263},{"x":-3,"y":3,"z":-2,"value":0.012716509},{"x":3,"y":4,"z":-4,"value":0.029653644},{"x":3,"y":4,"z":-3,"value":0.20749521},{"x":3,"y":4,"z":-2,"value":0.2838964},{"x":-3,"y":3,"z":3,"value":0.48362145},{"x":3,"y":4,"z":-1,"value":0.29524133},{"x":-3,"y":3,"z":4,"value":0.021064019},{"x":3,"y":4,"z":0,"value":0.29648617},{"x":3,"y":4,"z":1,"value":0.2764226},{"x":-5,"y":3,"z":-3,"value":0.19947746},{"x":3,"y":4,"z":2,"value":0.18173982},{"x":-5,"y":3,"z":-2,"value":0.32280436},{"x":1,"y":4,"z":-5,"value":0.064218454},{"x":-5,"y":3,"z":-1,"value":0.32815847},{"x":1,"y":4,"z":-4,"value":0.31820434},{"x":-5,"y":3,"z":0,"value":0.31691945},{"x":1,"y":4,"z":-3,"value":0.31937525},{"x":-5,"y":3,"z":1,"value":0.31547067},{"x":1,"y":4,"z":-2,"value":0.2844752},{"x":-5,"y":3,"z":2,"value":0.23721433},{"x":1,"y":4,"z":-1,"value":0.26484045},{"x":-5,"y":3,"z":3,"value":0.027414942},{"x":1,"y":4,"z":0,"value":0.2660945},{"x":1,"y":4,"z":1,"value":0.28483498},{"x":1,"y":4,"z":2,"value":0.31803232},{"x":1,"y":4,"z":3,"value":0.22658953},{"x":-1,"y":4,"z":-5,"value":0.15219438},{"x":-1,"y":4,"z":-4,"value":0.33949512},{"x":-1,"y":4,"z":-3,"value":0.3067149},{"x":-1,"y":4,"z":-2,"value":0.25900957},{"x":-1,"y":4,"z":-1,"value":0.25040787},{"x":-1,"y":4,"z":0,"value":0.2506105},{"x":-1,"y":4,"z":1,"value":0.2731549},{"x":-1,"y":4,"z":2,"value":0.31427902},{"x":-1,"y":4,"z":3,"value":0.31536785},{"x":-3,"y":4,"z":-4,"value":0.2745253},{"x":-3,"y":4,"z":-3,"value":0.37131578},{"x":-3,"y":4,"z":-2,"value":0.30065113},{"x":-3,"y":4,"z":-1,"value":0.26944035},{"x":-3,"y":4,"z":0,"value":0.29686603},{"x":-3,"y":4,"z":1,"value":0.3359804},{"x":-3,"y":4,"z":2,"value":0.36402437},{"x":-3,"y":4,"z":3,"value":0.19852999},{"x":-5,"y":4,"z":-2,"value":0.03495988},{"x":-5,"y":4,"z":-1,"value":0.073144116},{"x":-5,"y":4,"z":0,"value":0.07528036},{"x":1,"y":5,"z":-3,"value":0.022029757},{"x":-5,"y":4,"z":1,"value":0.044997122},{"x":1,"y":5,"z":-2,"value":0.054180887},{"x":1,"y":5,"z":-1,"value":0.058786},{"x":1,"y":5,"z":0,"value":0.053652335},{"x":1,"y":5,"z":1,"value":0.035186768},{"x":-1,"y":5,"z":-3,"value":0.057402264},{"x":-1,"y":5,"z":-2,"value":0.14257726},{"x":-1,"y":5,"z":-1,"value":0.178047},{"x":-1,"y":5,"z":0,"value":0.14254548},{"x":-1,"y":5,"z":1,"value":0.09260879},{"x":-1,"y":5,"z":2,"value":0.022471547},{"x":-3,"y":5,"z":-2,"value":0.045343425},{"x":-3,"y":5,"z":-1,"value":0.07760765},{"x":-3,"y":5,"z":0,"value":0.05979991},{"x":-3,"y":5,"z":1,"value":0.035265982}]}