{"cells":[{"x":7,"y":-10,"value":0.2409274},{"x":7,"y":-8,"value":0.08906041},{"x":7,"y":-7,"value":1},{"x":7,"y":-6,"value":0.123916745},{"x":7,"y":-5,"value":0.27164486},{"x":7,"y":-4,"value":0.32292393},{"x":7,"y":-3,"value":0.6398408},{"x":7,"y":-2,"value":0.09953945},{"x":7,"y":-1,"value":0.09908612},{"x":7,"y":0,"value":0.099716425},{"x":7,"y":1,"value":0.08324172},{"x":7,"y":2,"value":0.318449},{"x":7,"y":3,"value":0.37283817},{"x":7,"y":5,"value":0.053093612},{"x":7,"y":6,"value":0.12659994},{"x":7,"y":7,"value":0.19600198},{"x":7,"y":8,"value":0.15981632},{"x":8,"y":-11,"value":0.59770745},{"x":8,"y":-8,"value":0.076963894},{"x":8,"y":-6,"value":0.05299247},{"x":8,"y":-5,"value":0.0975856},{"x":8,"y":-4,"value":0.10807226},{"x":8,"y":-3,"value":0.10879126},{"x":8,"y":-2,"value":0.10706866},{"x":8,"y":-1,"value":0.10538441},{"x":8,"y":0,"value":0.68082607},{"x":8,"y":1,"value":0.113625176},{"x":8,"y":2,"value":0.14851563},{"x":8,"y":3,"value":0.16003253},{"x":8,"y":4,"value":0.91560864},{"x":8,"y":5,"value":0.20087609},{"x":8,"y":6,"value":0.21506703},{"x":8,"y":7,"value":0.11581312},{"x":8,"y":9,"value":0.17359719},{"x":9,"y":-11,"value":0.39919078},{"x":9,"y":-9,"value":0.43046758},{"x":9,"y":-8,"value":0.6337077},{"x":9,"y":-4,"value":0.42856938},{"x":9,"y":4,"value":0.30797818},{"x":10,"y":-6,"value":0.60402423},{"x":10,"y":-5,"value":0.13885275},{"x":10,"y":-4,"value":0.29945764},{"x":10,"y":-2,"value":0.39090124},{"x":10,"y":0,"value":0.4168371},{"x":10,"y":4,"value":0.2463077},{"x":10,"y":7,"value":0.45983943},{"x":10,"y":9,"value":0.40218577},{"x":-12,"y":0,"value":0.11100375},{"x":-12,"y":1,"value":0.21910146},{"x":-12,"y":2,"value":0.19687599},{"x":-12,"y":3,"value":0.052510165},{"x":-11,"y":-11,"value":0.15837502},{"x":-11,"y":-10,"value":0.19399768},{"x":-11,"y":-8,"value":0.14323527},{"x":-11,"y":-7,"value":0.16740337},{"x":-11,"y":-5,"value":0.43503353},{"x":-11,"y":-1,"value":0.1465726},{"x":-11,"y":0,"value":0.2108455},{"x":-11,"y":1,"value":0.17744495},{"x":-11,"y":2,"value":0.18830305},{"x":-11,"y":3,"value":0.16161723},{"x":-11,"y":4,"value":0.0360666},{"x":-11,"y":5,"value":0.81603366},{"x":-11,"y":7,"value":0.4809437},{"x":-11,"y":8,"value":0.18556044},{"x":-10,"y":-8,"value":0.37934998},{"x":-10,"y":-4,"value":0.07905324},{"x":-10,"y":-3,"value":0.12492609},{"x":-10,"y":-2,"value":0.16054672},{"x":-10,"y":-1,"value":0.16860816},{"x":-10,"y":0,"value":0.1483293},{"x":-10,"y":1,"value":0.12790197},{"x":-10,"y":2,"value":0.145856},{"x":-10,"y":3,"value":0.6153377},{"x":-10,"y":4,"value":0.17862986},{"x":-10,"y":5,"value":0.7523603},{"x":-10,"y":6,"value":0.5947106},{"x":-9,"y":-11,"value":0.65650654},{"x":-9,"y":-9,"value":0.022900313},{"x":-9,"y":-7,"value":0.06468348},{"x":-9,"y":-6,"value":0.12358278},{"x":-9,"y":-5,"value":0.13650353},{"x":-9,"y":-4,"value":0.13378778},{"x":-9,"y":-3,"value":0.7768684},{"x":-9,"y":-2,"value":0.893578},{"x":-9,"y":-1,"value":0.3722311},{"x":-9,"y":0,"value":0.05167705},{"x":-9,"y":1,"value":0.43944705},{"x":-9,"y":2,"value":0.5196914},{"x":-9,"y":3,"value":0.07514556},{"x":-9,"y":4,"value":0.87902606},{"x":-9,"y":5,"value":0.7047906},{"x":-9,"y":6,"value":0.79235995},{"x":-9,"y":7,"value":0.21902949},{"x":-8,"y":-8,"value":0.570894},{"x":-8,"y":-7,"value":0.7102507},{"x":-8,"y":-6,"value":0.09928247},{"x":-8,"y":-5,"value":0.031913724},{"x":-8,"y":0,"value":0.347033},{"x":-8,"y":1,"value":0.28262615},{"x":-8,"y":2,"value":0.73280686},{"x":-8,"y":3,"value":0.646781},{"x":-8,"y":7,"value":0.38058746},{"x":-8,"y":8,"value":0.9954757},{"x":-8,"y":9,"value":0.19141266},{"x":-8,"y":10,"value":0.7931708},{"x":-7,"y":-10,"value":0.47841942},{"x":-7,"y":-9,"value":0.38016227},{"x":-7,"y":-8,"value":0.3233088},{"x":-7,"y":-7,"value":0.16134825},{"x":-7,"y":-2,"value":0.017313048},{"x":-7,"y":4,"value":0.01068712},{"x":-7,"y":8,"value":0.3561729},{"x":-7,"y":9,"value":0.17183575},{"x":-7,"y":10,"value":0.95437515},{"x":-6,"y":-11,"value":0.77666456},{"x":-6,"y":-10,"value":0.09136824},{"x":-6,"y":-9,"value":0.11912057},{"x":-6,"y":-7,"value":0.21931568},{"x":-6,"y":-5,"value":0.045328528},{"x":-6,"y":-1,"value":0.38296607},{"x":-6,"y":1,"value":0.2505393},{"x":-6,"y":2,"value":0.50348616},{"x":-6,"y":6,"value":0.16917562},{"x":-6,"y":9,"value":0.08142134},{"x":-6,"y":10,"value":0.09669703},{"x":-5,"y":-11,"value":0.07649913},{"x":-5,"y":-10,"value":0.123707935},{"x":-5,"y":-9,"value":0.33872557},{"x":-5,"y":-4,"value":0.67486733},{"x":-5,"y":-2,"value":0.19440325},{"x":-5,"y":1,"value":0.07234011},{"x":-5,"y":2,"value":0.5506062},{"x":-5,"y":5,"value":0.41372213},{"x":-5,"y":9,"value":0.07408925},{"x":-5,"y":10,"value":0.13876723},{"x":-4,"y":-11,"value":0.11067124},{"x":-4,"y":-10,"value":0.8424336},{"x":-4,"y":-9,"value":0.019925272},{"x":-4,"y":-8,"value":0.14136988},{"x":-4,"y":-5,"value":0.1284861},{"x":-4,"y":-3,"value":0.23561874},{"x":-4,"y":1,"value":0.4334055},{"x":-4,"y":2,"value":0.51972795},{"x":-4,"y":3,"value":0.39594087},{"x":-4,"y":9,"value":0.07346677},{"x":-4,"y":10,"value":1},{"x":-3,"y":-11,"value":0.13515556},{"x":-3,"y":-10,"value":0.84231716},{"x":-3,"y":-9,"value":0.59386307},{"x":-3,"y":-5,"value":0.2553622},{"x":-3,"y":-3,"value":0.5919988},{"x":-3,"y":5,"value":0.121532016},{"x":-3,"y":9,"value":0.85349447},{"x":-3,"y":10,"value":0.9587032},{"x":-2,"y":-11,"value":0.17902364},{"x":-2,"y":-10,"value":0.09238962},{"x":-2,"y":-9,"value":0.51308954},{"x":-2,"y":-7,"value":0.5569653},{"x":-2,"y":-5,"value":0.23696563},{"x":-2,"y":5,"value":0.6369641},{"x":-2,"y":6,"value":0.36774966},{"x":-2,"y":9,"value":0.5200541},{"x":-2,"y":10,"value":0.21352834},{"x":-1,"y":-11,"value":0.20248018},{"x":-1,"y":-10,"value":0.07297068},{"x":-1,"y":-9,"value":0.4948476},{"x":-1,"y":-6,"value":0.6715831},{"x":-1,"y":-5,"value":0.53881466},{"x":-1,"y":-3,"value":0.5424021},{"x":-1,"y":-2,"value":0.2988151},{"x":-1,"y":2,"value":0.63363194},{"x":-1,"y":4,"value":0.22082126},{"x":-1,"y":9,"value":0.6178952},{"x":-1,"y":10,"value":0.90463966},{"x":0,"y":-11,"value":1},{"x":0,"y":-10,"value":0.7899965},{"x":0,"y":-5,"value":0.6416867},{"x":0,"y":-4,"value":0.5372169},{"x":0,"y":-2,"value":0.58595496},{"x":0,"y":-1,"value":0.63885164},{"x":0,"y":6,"value":0.33421886},{"x":0,"y":7,"value":0.07246759},{"x":0,"y":9,"value":0.48626003},{"x":0,"y":10,"value":0.14414994},{"x":0,"y":11,"value":0.20265825},{"x":1,"y":-11,"value":0.17870487},{"x":1,"y":-10,"value":0.0563125},{"x":1,"y":-6,"value":0.654354},{"x":1,"y":-4,"value":0.3803859},{"x":1,"y":-2,"value":0.3877821},{"x":1,"y":0,"value":0.27304167},{"x":1,"y":2,"value":0.5617424},{"x":1,"y":3,"value":0.23099938},{"x":1,"y":5,"value":0.47437248},{"x":1,"y":9,"value":0.5227417},{"x":1,"y":10,"value":0.05248425},{"x":1,"y":11,"value":0.26299098},{"x":1,"y":12,"value":0.1197363},{"x":2,"y":-11,"value":0.4229181},{"x":2,"y":-10,"value":0.059155464},{"x":2,"y":-5,"value":0.055684783},{"x":2,"y":-1,"value":0.33589545},{"x":2,"y":1,"value":0.12849545},{"x":2,"y":3,"value":0.034543782},{"x":2,"y":4,"value":0.3032492},{"x":2,"y":5,"value":0.483288},{"x":2,"y":9,"value":0.423609},{"x":2,"y":10,"value":0.06298429},{"x":2,"y":11,"value":0.26808476},{"x":2,"y":12,"value":0.1039879},{"x":3,"y":-11,"value":1},{"x":3,"y":-10,"value":0.5835562},{"x":3,"y":-6,"value":0.31223792},{"x":3,"y":-4,"value":0.18892449},{"x":3,"y":4,"value":0.012886055},{"x":3,"y":5,"value":0.6301829},{"x":3,"y":8,"value":0.4646792},{"x":3,"y":9,"value":0.7863647},{"x":3,"y":10,"value":0.20612094},{"x":3,"y":11,"value":0.19518062},{"x":4,"y":-11,"value":0.13251464},{"x":4,"y":-10,"value":0.93780756},{"x":4,"y":-8,"value":0.3248755},{"x":4,"y":-1,"value":0.031006046},{"x":4,"y":0,"value":0.60702616},{"x":4,"y":4,"value":0.6022555},{"x":4,"y":8,"value":0.06584873},{"x":4,"y":9,"value":1},{"x":4,"y":10,"value":0.49261424},{"x":5,"y":-10,"value":0.14320995},{"x":5,"y":-9,"value":0.12029633},{"x":5,"y":-7,"value":0.43569356},{"x":5,"y":-6,"value":0.08807378},{"x":5,"y":-3,"value":0.2964114},{"x":5,"y":0,"value":0.54785967},{"x":5,"y":4,"value":0.47423035},{"x":5,"y":6,"value":0.73356736},{"x":5,"y":7,"value":0.3636307},{"x":5,"y":8,"value":1},{"x":5,"y":9,"value":0.2117659},{"x":6,"y":-9,"value":0.119481966},{"x":6,"y":-8,"value":0.57689863},{"x":6,"y":-7,"value":0.44315562},{"x":6,"y":-3,"value":0.19223683},{"x":6,"y":6,"value":0.020675207},{"x":6,"y":7,"value":1},{"x":6,"y":8,"value":0.19769563},{"x":6,"y":9,"value":0.09140768},{"x":6,"y":10,"value":0.74109536}]}