{"cells":[{"x":-18,"y":-3,"value":0.032164004},{"x":-18,"y":-2,"value":0.07619124},{"x":-18,"y":-1,"value":0.075987},{"x":-18,"y":0,"value":0.035003375},{"x":-17,"y":-4,"value":0.078206204},{"x":-17,"y":-3,"value":0.1381407},{"x":-17,"y":-2,"value":0.15238748},{"x":-17,"y":-1,"value":0.14665566},{"x":-17,"y":0,"value":0.117682666},{"x":-17,"y":1,"value":0.061766114},{"x":-16,"y":-5,"value":0.13112682},{"x":-16,"y":-4,"value":0.21805084},{"x":-16,"y":-3,"value":0.22548833},{"x":-16,"y":-2,"value":0.18721828},{"x":-16,"y":-1,"value":0.18874016},{"x":-16,"y":0,"value":0.21244697},{"x":-16,"y":1,"value":0.1704574},{"x":-16,"y":2,"value":0.072214596},{"x":-15,"y":-6,"value":0.19171716},{"x":-15,"y":-5,"value":0.29887816},{"x":-15,"y":-4,"value":0.4508939},{"x":-15,"y":-3,"value":0.51026005},{"x":-15,"y":-2,"value":0.39170706},{"x":-15,"y":-1,"value":0.4823941},{"x":-15,"y":0,"value":0.69839066},{"x":-15,"y":1,"value":0.7534516},{"x":-15,"y":2,"value":0.87807024},{"x":-15,"y":3,"value":0.29463395},{"x":-14,"y":-7,"value":0.18003455},{"x":-14,"y":-6,"value":0.15941837},{"x":-14,"y":-5,"value":0.05014322},{"x":-14,"y":-4,"value":0.2975595},{"x":-14,"y":-3,"value":0.7267723},{"x":-14,"y":-2,"value":0.68810326},{"x":-14,"y":-1,"value":0.9575002},{"x":-14,"y":0,"value":1},{"x":-14,"y":1,"value":0.03696561},{"x":-14,"y":3,"value":0.48464036},{"x":-14,"y":4,"value":0.35372737},{"x":-13,"y":-7,"value":0.20426302},{"x":-13,"y":-3,"value":0.5566117},{"x":-13,"y":-2,"value":1},{"x":-13,"y":-1,"value":0.9440341},{"x":-13,"y":0,"value":0.13095602},{"x":-13,"y":4,"value":0.5709762},{"x":-12,"y":-8,"value":0.18987352},{"x":-12,"y":-3,"value":0.6386509},{"x":-12,"y":-2,"value":1},{"x":-12,"y":-1,"value":0.98856556},{"x":-12,"y":4,"value":0.16987927},{"x":-12,"y":5,"value":0.040559605},{"x":-11,"y":-8,"value":0.46565083},{"x":-11,"y":-3,"value":0.49438238},{"x":-11,"y":-2,"value":0.5557935},{"x":-11,"y":-1,"value":0.5829447},{"x":-11,"y":0,"value":0.17395273},{"x":-11,"y":4,"value":0.058040496},{"x":-11,"y":5,"value":0.46572268},{"x":-10,"y":-8,"value":0.46240413},{"x":-10,"y":-3,"value":0.152899},{"x":-10,"y":-2,"value":0.2107447},{"x":-10,"y":-1,"value":0.21060875},{"x":-10,"y":0,"value":0.053691834},{"x":-10,"y":4,"value":0.238077},{"x":-10,"y":5,"value":0.20023862},{"x":-10,"y":9,"value":0.10820634},{"x":-10,"y":10,"value":0.42640635},{"x":-10,"y":11,"value":0.4206649},{"x":-10,"y":12,"value":0.3159373},{"x":-9,"y":-8,"value":0.060221683},{"x":-9,"y":-7,"value":0.53235614},{"x":-9,"y":-3,"value":0.6620629},{"x":-9,"y":-2,"value":0.65986925},{"x":-9,"y":-1,"value":0.49444082},{"x":-9,"y":0,"value":0.084902026},{"x":-9,"y":4,"value":0.5098186},{"x":-9,"y":5,"value":0.10343909},{"x":-9,"y":6,"value":0.03823579},{"x":-9,"y":8,"value":0.06308913},{"x":-9,"y":9,"value":0.44891974},{"x":-9,"y":10,"value":0.17635591},{"x":-9,"y":11,"value":0.04940499},{"x":-9,"y":13,"value":0.32257903},{"x":-9,"y":14,"value":0.7041962},{"x":-9,"y":15,"value":0.46885884},{"x":-9,"y":16,"value":0.046604514},{"x":-8,"y":-7,"value":0.49904713},{"x":-8,"y":-6,"value":0.5810388},{"x":-8,"y":-4,"value":0.17638412},{"x":-8,"y":-3,"value":0.31061146},{"x":-8,"y":-2,"value":0.019376427},{"x":-8,"y":4,"value":0.27708033},{"x":-8,"y":7,"value":0.41123134},{"x":-8,"y":15,"value":0.0733228},{"x":-8,"y":16,"value":0.37622035},{"x":-8,"y":17,"value":0.18032257},{"x":-7,"y":-6,"value":0.9993745},{"x":-7,"y":-5,"value":0.85759276},{"x":-7,"y":3,"value":0.1459547},{"x":-7,"y":4,"value":0.20142171},{"x":-7,"y":5,"value":0.18241923},{"x":-7,"y":6,"value":0.30589},{"x":-7,"y":16,"value":0.14861177},{"x":-7,"y":17,"value":0.4433397},{"x":-7,"y":18,"value":0.06676224},{"x":-6,"y":-6,"value":0.8913648},{"x":-6,"y":-5,"value":0.27250028},{"x":-6,"y":3,"value":0.20555398},{"x":-6,"y":4,"value":0.23314422},{"x":-6,"y":5,"value":0.26071453},{"x":-6,"y":15,"value":0.04249095},{"x":-6,"y":16,"value":0.2409547},{"x":-6,"y":17,"value":0.49967808},{"x":-6,"y":18,"value":0.26777828},{"x":-5,"y":-6,"value":0.548434},{"x":-5,"y":-5,"value":0.2970155},{"x":-5,"y":2,"value":0.061629534},{"x":-5,"y":3,"value":0.31875283},{"x":-5,"y":4,"value":0.29930323},{"x":-5,"y":5,"value":0.081627265},{"x":-5,"y":12,"value":0.16300741},{"x":-5,"y":13,"value":0.2715118},{"x":-5,"y":14,"value":0.27517334},{"x":-5,"y":15,"value":0.38645506},{"x":-5,"y":16,"value":0.49335766},{"x":-5,"y":17,"value":0.5542333},{"x":-5,"y":18,"value":0.34638482},{"x":-4,"y":-6,"value":0.39194143},{"x":-4,"y":-5,"value":0.33226386},{"x":-4,"y":1,"value":0.12062356},{"x":-4,"y":2,"value":0.386536},{"x":-4,"y":3,"value":0.34175628},{"x":-4,"y":4,"value":0.43002328},{"x":-4,"y":10,"value":0.57067215},{"x":-4,"y":11,"value":0.5284953},{"x":-4,"y":12,"value":0.7005999},{"x":-4,"y":13,"value":0.8723558},{"x":-4,"y":14,"value":0.91997135},{"x":-4,"y":15,"value":0.7213798},{"x":-4,"y":16,"value":0.60826},{"x":-4,"y":17,"value":0.56118965},{"x":-4,"y":18,"value":0.35523593},{"x":-3,"y":-6,"value":0.3881519},{"x":-3,"y":-5,"value":0.365194},{"x":-3,"y":0,"value":0.1389119},{"x":-3,"y":1,"value":0.09827204},{"x":-3,"y":3,"value":0.012394226},{"x":-3,"y":4,"value":0.43817925},{"x":-3,"y":5,"value":0.14227523},{"x":-3,"y":9,"value":0.93709093},{"x":-3,"y":10,"value":1},{"x":-3,"y":11,"value":0.7508132},{"x":-3,"y":12,"value":0.7054392},{"x":-3,"y":13,"value":1},{"x":-3,"y":14,"value":0.980863},{"x":-3,"y":15,"value":0.6878052},{"x":-3,"y":16,"value":0.525428},{"x":-3,"y":17,"value":0.5352766},{"x":-3,"y":18,"value":0.3627454},{"x":-2,"y":-6,"value":0.33952945},{"x":-2,"y":-5,"value":0.3764694},{"x":-2,"y":-4,"value":0.1274415},{"x":-2,"y":-1,"value":0.248162},{"x":-2,"y":0,"value":0.9589048},{"x":-2,"y":1,"value":0.07702898},{"x":-2,"y":4,"value":0.25073084},{"x":-2,"y":5,"value":0.40781265},{"x":-2,"y":9,"value":1},{"x":-2,"y":10,"value":1},{"x":-2,"y":11,"value":1},{"x":-2,"y":12,"value":1},{"x":-2,"y":13,"value":0.5489202},{"x":-2,"y":14,"value":0.073709555},{"x":-2,"y":15,"value":0.06999148},{"x":-2,"y":16,"value":0.08996558},{"x":-2,"y":17,"value":0.34753677},{"x":-2,"y":18,"value":0.33663902},{"x":-1,"y":-6,"value":0.29501104},{"x":-1,"y":-5,"value":0.3855911},{"x":-1,"y":-4,"value":0.21871978},{"x":-1,"y":-3,"value":0.1890494},{"x":-1,"y":-1,"value":0.47054237},{"x":-1,"y":0,"value":0.10242589},{"x":-1,"y":1,"value":0.08561219},{"x":-1,"y":2,"value":0.19257455},{"x":-1,"y":4,"value":0.17007819},{"x":-1,"y":5,"value":0.43081987},{"x":-1,"y":10,"value":0.1762008},{"x":-1,"y":17,"value":0.12288146},{"x":-1,"y":18,"value":0.249715},{"x":0,"y":-6,"value":0.07194684},{"x":0,"y":-5,"value":0.37425318},{"x":0,"y":-4,"value":0.5031782},{"x":0,"y":-3,"value":0.039533414},{"x":0,"y":-1,"value":0.2474101},{"x":0,"y":0,"value":0.68325335},{"x":0,"y":1,"value":0.31654423},{"x":0,"y":2,"value":0.5707829},{"x":0,"y":3,"value":0.0916227},{"x":0,"y":4,"value":0.32952842},{"x":0,"y":5,"value":0.26813555},{"x":0,"y":17,"value":0.07193505},{"x":0,"y":18,"value":0.13003913},{"x":1,"y":-5,"value":0.33789366},{"x":1,"y":-4,"value":0.32158655},{"x":1,"y":-3,"value":0.1479254},{"x":1,"y":-2,"value":0.21390915},{"x":1,"y":0,"value":0.3500479},{"x":1,"y":1,"value":0.3041946},{"x":1,"y":2,"value":0.3263232},{"x":1,"y":3,"value":0.33455303},{"x":1,"y":4,"value":0.17362502},{"x":1,"y":17,"value":0.13819098},{"x":2,"y":-5,"value":0.2021966},{"x":2,"y":-4,"value":0.39230078},{"x":2,"y":-3,"value":0.29950005},{"x":2,"y":-2,"value":0.16090035},{"x":2,"y":-1,"value":0.15346168},{"x":2,"y":17,"value":0.17657813},{"x":3,"y":-4,"value":0.19547607},{"x":3,"y":-3,"value":0.31645423},{"x":3,"y":-2,"value":0.34930712},{"x":3,"y":-1,"value":0.26059058},{"x":3,"y":0,"value":0.06253318},{"x":3,"y":17,"value":0.17575628},{"x":4,"y":-5,"value":0.026158303},{"x":4,"y":-4,"value":0.15605052},{"x":4,"y":-3,"value":0.32963368},{"x":4,"y":-2,"value":0.3707602},{"x":4,"y":-1,"value":0.32581425},{"x":4,"y":0,"value":0.3192231},{"x":4,"y":1,"value":0.06994654},{"x":4,"y":17,"value":0.17254232},{"x":5,"y":-4,"value":0.030763961},{"x":5,"y":-3,"value":0.44246924},{"x":5,"y":-2,"value":0.5717879},{"x":5,"y":-1,"value":0.6620158},{"x":5,"y":0,"value":0.77315545},{"x":5,"y":1,"value":0.35672128},{"x":5,"y":2,"value":0.123384565},{"x":5,"y":8,"value":0.049415834},{"x":5,"y":16,"value":0.066643454},{"x":5,"y":17,"value":0.19773972},{"x":6,"y":-1,"value":0.14290974},{"x":6,"y":0,"value":0.5269014},{"x":6,"y":1,"value":0.49027282},{"x":6,"y":2,"value":0.32736528},{"x":6,"y":3,"value":0.19559975},{"x":6,"y":7,"value":0.16296324},{"x":6,"y":8,"value":0.3808636},{"x":6,"y":9,"value":0.8378283},{"x":6,"y":10,"value":1},{"x":6,"y":11,"value":1},{"x":6,"y":12,"value":1},{"x":6,"y":13,"value":1},{"x":6,"y":14,"value":0.27423915},{"x":6,"y":15,"value":0.19563498},{"x":6,"y":16,"value":0.2345115},{"x":6,"y":17,"value":0.23708564},{"x":6,"y":18,"value":0.029457975},{"x":7,"y":2,"value":0.43428653},{"x":7,"y":3,"value":0.58982074},{"x":7,"y":4,"value":0.13746873},{"x":7,"y":8,"value":0.23462251},{"x":7,"y":9,"value":0.73846114},{"x":7,"y":10,"value":1},{"x":7,"y":11,"value":0.70068526},{"x":7,"y":12,"value":0.9238271},{"x":7,"y":13,"value":1},{"x":7,"y":14,"value":0.7457565},{"x":7,"y":15,"value":0.5655794},{"x":7,"y":16,"value":0.4316998},{"x":7,"y":17,"value":0.29154217},{"x":7,"y":18,"value":0.034627475},{"x":8,"y":3,"value":0.37675703},{"x":8,"y":4,"value":0.89107555},{"x":8,"y":5,"value":0.02658472},{"x":8,"y":9,"value":0.29716903},{"x":8,"y":10,"value":0.90135765},{"x":8,"y":11,"value":1},{"x":8,"y":12,"value":1},{"x":8,"y":13,"value":0.85950035},{"x":8,"y":14,"value":0.74011827},{"x":8,"y":15,"value":0.6152224},{"x":8,"y":16,"value":0.48833868},{"x":8,"y":17,"value":0.27655303},{"x":8,"y":18,"value":0.016850019},{"x":9,"y":3,"value":0.06577362},{"x":9,"y":4,"value":0.44281533},{"x":9,"y":5,"value":0.22606836},{"x":9,"y":11,"value":0.22659865},{"x":9,"y":12,"value":0.60183686},{"x":9,"y":13,"value":0.563665},{"x":9,"y":14,"value":0.5205573},{"x":9,"y":15,"value":0.47233814},{"x":9,"y":16,"value":0.42563713},{"x":9,"y":17,"value":0.19731832},{"x":10,"y":4,"value":0.22743374},{"x":10,"y":5,"value":0.2840464},{"x":10,"y":6,"value":0.032860126},{"x":10,"y":14,"value":0.08019508},{"x":10,"y":15,"value":0.2695618},{"x":10,"y":16,"value":0.30257106},{"x":10,"y":17,"value":0.0899088},{"x":11,"y":5,"value":0.27628803},{"x":11,"y":6,"value":0.40901172},{"x":11,"y":14,"value":0.026172519},{"x":11,"y":15,"value":0.17766011},{"x":11,"y":16,"value":0.16752921},{"x":12,"y":7,"value":0.76389635},{"x":12,"y":8,"value":0.20382233},{"x":12,"y":14,"value":0.1307816},{"x":12,"y":15,"value":0.15885258},{"x":12,"y":16,"value":0.011773789},{"x":13,"y":9,"value":0.070313334},{"x":13,"y":10,"value":0.3727149},{"x":13,"y":11,"value":0.296052},{"x":13,"y":12,"value":0.22125916},{"x":13,"y":13,"value":0.16975413},{"x":13,"y":14,"value":0.05618569}]}