{"cells":[{"x":-2,"y":-2,"z":-2,"value":0.8036047},{"x":-2,"y":-2,"z":-1,"value":0.69668436},{"x":-2,"y":-2,"z":1,"value":0.52232814},{"x":-2,"y":-1,"z":-1,"value":0.19986156},{"x":-2,"y":-1,"z":0,"value":0.7426872},{"x":-2,"y":-1,"z":1,"value":0.82604206},{"x":-2,"y":0,"z":-2,"value":0.55906296},{"x":-2,"y":0,"z":-1,"value":0.69092494},{"x":-2,"y":0,"z":0,"value":0.13539888},{"x":-2,"y":1,"z":-2,"value":0.7734396},{"x":-2,"y":1,"z":-1,"value":0.54481995},{"x":-2,"y":1,"z":0,"value":0.5919025},{"x":-2,"y":1,"z":1,"value":0.45726195},{"x":-1,"y":-2,"z":-1,"value":0.7781196},{"x":-1,"y":-2,"z":0,"value":0.78704995},{"x":-1,"y":-2,"z":1,"value":0.42789432},{"x":-1,"y":-1,"z":-2,"value":0.9400399},{"x":-1,"y":-1,"z":-1,"value":0.0789241},{"x":-1,"y":-1,"z":0,"value":0.74432683},{"x":-1,"y":-1,"z":1,"value":0.69118804},{"x":-1,"y":0,"z":-2,"value":1},{"x":-1,"y":0,"z":-1,"value":0.08270605},{"x":-1,"y":0,"z":0,"value":0.97644806},{"x":-1,"y":0,"z":1,"value":0.709188},{"x":-1,"y":1,"z":-1,"value":0.9832315},{"x":-1,"y":1,"z":0,"value":0.6536372},{"x":-1,"y":1,"z":1,"value":0.35633042},{"x":0,"y":-2,"z":-2,"value":0.45056283},{"x":0,"y":-2,"z":-1,"value":0.7339307},{"x":0,"y":-2,"z":0,"value":0.8897513},{"x":0,"y":-2,"z":1,"value":0.5885078},{"x":0,"y":-1,"z":-2,"value":0.95703244},{"x":0,"y":-1,"z":-1,"value":0.098095894},{"x":0,"y":-1,"z":0,"value":0.17976978},{"x":0,"y":-1,"z":1,"value":0.8578719},{"x":0,"y":0,"z":-2,"value":1},{"x":0,"y":0,"z":-1,"value":0.0129722},{"x":0,"y":0,"z":0,"value":0.9447859},{"x":0,"y":0,"z":1,"value":0.86929613},{"x":0,"y":1,"z":-2,"value":0.51547694},{"x":0,"y":1,"z":-1,"value":0.19371372},{"x":0,"y":1,"z":0,"value":0.18684816},{"x":0,"y":1,"z":1,"value":0.6185453},{"x":1,"y":-2,"z":-2,"value":0.73747844},{"x":1,"y":-2,"z":-1,"value":0.74457914},{"x":1,"y":-2,"z":0,"value":0.50363743},{"x":1,"y":-2,"z":1,"value":0.7632258},{"x":1,"y":-1,"z":-2,"value":0.63357925},{"x":1,"y":-1,"z":-1,"value":1},{"x":1,"y":-1,"z":0,"value":0.17289197},{"x":1,"y":-1,"z":1,"value":0.7635744},{"x":1,"y":0,"z":-1,"value":0.14553197},{"x":1,"y":0,"z":0,"value":0.16450265},{"x":1,"y":0,"z":1,"value":0.39331466},{"x":1,"y":1,"z":-2,"value":0.7518779},{"x":1,"y":1,"z":-1,"value":0.077321395},{"x":1,"y":1,"z":0,"value":0.9763828},{"x":1,"y":1,"z":1,"value":0.33971968}]}